{
    "id": "BR_B+_D*+_D*0bar_K0",
    "latex": "{\\cal B}(B^+ \\to D^*(2010)^+ \\bar{D}^*(2007)^0 K^0)",
    "chi2": 0.0,
    "ndf": 0,
    "p": 1,
    "value": 0.00917,
    "filter": {
        "BR": 1,
        "Bu": 1,
        "D*+": 1,
        "D*0": 1,
        "K0": 1
    },
    "unit_exp": -3,
    "digits": 1,
    "error": 0.0012242957157175018,
    "pdg_value": 0.00381,
    "pdg_error": 0.000386005181312376,
    "pdg_link": "https://pdglive.lbl.gov/BranchingRatio.action?desig=330&parCode=S041",
    "measurements": [
        {
            "experiment": "BaBar",
            "link": "https://inspirehep.net/literature/877816",
            "text": "Phys.Rev.D <b>83</b>,032004 (2011)",
            "value": 0.00917,
            "stat_error": 0.00083,
            "syst_error": 0.0009000000000000001,
            "digits": 2,
            "chi2": 0.0
        }
    ],
    "correlations": []
}